pylude/__init__.py
pylude-0.0.1.dist-info/DESCRIPTION.rst
pylude-0.0.1.dist-info/METADATA
pylude-0.0.1.dist-info/RECORD
pylude-0.0.1.dist-info/WHEEL
pylude-0.0.1.dist-info/metadata.json
pylude-0.0.1.dist-info/top_level.txt
