Metadata-Version: 2.0
Name: pylude
Version: 0.0.1
Summary: A library trying to clone the Haskell-Prelude for python3
Home-page: UNKNOWN
Author: Tobias Weise
Author-email: tobias_weise@gmx.de
License: BSD3
Keywords: prelude haskell function functional lambda list tuple higherorder
Platform: UNKNOWN
Classifier: Development Status :: 4 - Beta
Classifier: Intended Audience :: Developers
Classifier: License :: OSI Approved :: BSD License
Classifier: Operating System :: OS Independent
Classifier: Programming Language :: Python :: 3
Classifier: Topic :: Software Development
Classifier: Topic :: Software Development :: Libraries
Classifier: Topic :: Utilities
